hanzo_tools/__init__.py
hanzo_tools/vector/__init__.py
hanzo_tools/vector/ast_analyzer.py
hanzo_tools/vector/git_ingester.py
hanzo_tools/vector/index_tool.py
hanzo_tools/vector/infinity_store.py
hanzo_tools/vector/mock_infinity.py
hanzo_tools/vector/project_manager.py
hanzo_tools/vector/vector.py
hanzo_tools/vector/vector_index.py
hanzo_tools/vector/vector_search.py
hanzo_tools_vector-0.2.0.dist-info/METADATA
hanzo_tools_vector-0.2.0.dist-info/WHEEL
hanzo_tools_vector-0.2.0.dist-info/entry_points.txt
hanzo_tools_vector-0.2.0.dist-info/top_level.txt
hanzo_tools_vector-0.2.0.dist-info/RECORD
